random_partition_py-0.2.0.dist-info/METADATA
random_partition_py-0.2.0.dist-info/WHEEL
random_partition_py/__init__.py
random_partition_py/random_partition_py.cpython-310-x86_64-linux-gnu.so
random_partition_py-0.2.0.dist-info/RECORD
