Metadata-Version: 2.1
Name: random-partition-py
Version: 0.2.0
Classifier: Programming Language :: Rust
Classifier: Programming Language :: Python :: Implementation :: CPython
Classifier: Programming Language :: Python :: Implementation :: PyPy
Summary: Generate approximately uniformly distributed random integer partitions.
Keywords: random,partition,mathematics
Author: Stefan Volz
License: MIT OR Apache-2.0
Requires-Python: >=3.7
Project-URL: Homepage, https://github.com/SV-97/random-partition
Project-URL: Bug Tracker, https://github.com/SV-97/random-partition/issues
